aws_creds_replace/__init__.py
aws_creds_replace/main.py
aws_creds_replace-0.0.3.dist-info/METADATA
aws_creds_replace-0.0.3.dist-info/WHEEL
aws_creds_replace-0.0.3.dist-info/entry_points.txt
aws_creds_replace-0.0.3.dist-info/top_level.txt
aws_creds_replace-0.0.3.dist-info/RECORD
